capstone_gt/__init__.py
capstone_gt/arm.py
capstone_gt/arm64.py
capstone_gt/arm64_const.py
capstone_gt/arm_const.py
capstone_gt/bpf.py
capstone_gt/bpf_const.py
capstone_gt/evm.py
capstone_gt/evm_const.py
capstone_gt/m680x.py
capstone_gt/m680x_const.py
capstone_gt/m68k.py
capstone_gt/m68k_const.py
capstone_gt/mips.py
capstone_gt/mips_const.py
capstone_gt/mos65xx.py
capstone_gt/mos65xx_const.py
capstone_gt/ppc.py
capstone_gt/ppc_const.py
capstone_gt/riscv.py
capstone_gt/riscv_const.py
capstone_gt/sh.py
capstone_gt/sh_const.py
capstone_gt/sparc.py
capstone_gt/sparc_const.py
capstone_gt/systemz.py
capstone_gt/sysz_const.py
capstone_gt/tms320c64x.py
capstone_gt/tms320c64x_const.py
capstone_gt/tricore.py
capstone_gt/tricore_const.py
capstone_gt/wasm.py
capstone_gt/wasm_const.py
capstone_gt/x86.py
capstone_gt/x86_const.py
capstone_gt/xcore.py
capstone_gt/xcore_const.py
capstone_gt/include/capstone/arm.h
capstone_gt/include/capstone/arm64.h
capstone_gt/include/capstone/bpf.h
capstone_gt/include/capstone/capstone.h
capstone_gt/include/capstone/evm.h
capstone_gt/include/capstone/m680x.h
capstone_gt/include/capstone/m68k.h
capstone_gt/include/capstone/mips.h
capstone_gt/include/capstone/mos65xx.h
capstone_gt/include/capstone/platform.h
capstone_gt/include/capstone/ppc.h
capstone_gt/include/capstone/riscv.h
capstone_gt/include/capstone/sh.h
capstone_gt/include/capstone/sparc.h
capstone_gt/include/capstone/systemz.h
capstone_gt/include/capstone/tms320c64x.h
capstone_gt/include/capstone/tricore.h
capstone_gt/include/capstone/wasm.h
capstone_gt/include/capstone/x86.h
capstone_gt/include/capstone/xcore.h
capstone_gt/lib/capstone.dll
capstone_gt-5.0.1.dist-info/LICENSE.TXT
capstone_gt-5.0.1.dist-info/METADATA
capstone_gt-5.0.1.dist-info/WHEEL
capstone_gt-5.0.1.dist-info/top_level.txt
capstone_gt-5.0.1.dist-info/zip-safe
capstone_gt-5.0.1.dist-info/RECORD
