Metadata-Version: 2.1
Name: capstone-gt
Version: 5.0.1
Summary: GrammaTech's fork of the Capstone disassembly engine.
Home-page: https://www.capstone-engine.org
Author: Nguyen Anh Quynh
Author-email: aquynh@gmail.com
License: UNKNOWN
Platform: UNKNOWN
Classifier: License :: OSI Approved :: BSD License
Classifier: Programming Language :: Python :: 2
Classifier: Programming Language :: Python :: 2.7
Classifier: Programming Language :: Python :: 3
Requires-Python: >=2.7, !=3.0.*, !=3.1.*, !=3.2.*, !=3.3.*
